CHANGES
MANIFEST.in
README.rst
requirements-test.txt
setup.py
DDLockClient.egg-info/PKG-INFO
DDLockClient.egg-info/SOURCES.txt
DDLockClient.egg-info/dependency_links.txt
DDLockClient.egg-info/top_level.txt
ddlockclient/__init__.py
tests/__init__.py
tests/test_client.py