Metadata-Version: 1.0
Name: DDLockClient
Version: 0.1.1
Summary: Python client library for the Danga distributed lock daemon
Home-page: http://github.com/stanimoto/python-ddlockclient
Author: Satoshi Tanimoto
Author-email: tanimoto.satoshi@gmail.com
License: Apache
Platform: UNKNOWN
Classifier: Development Status :: 5 - Production/Stable
Classifier: Intended Audience :: Developers
Classifier: Programming Language :: Python
Classifier: Programming Language :: Python :: 2.6
Classifier: License :: OSI Approved :: Apache Software License
